llama_index/readers/web/__init__.py
llama_index/readers/web/agentql_web/README.md
llama_index/readers/web/agentql_web/__init__.py
llama_index/readers/web/agentql_web/base.py
llama_index/readers/web/async_web/README.md
llama_index/readers/web/async_web/__init__.py
llama_index/readers/web/async_web/base.py
llama_index/readers/web/beautiful_soup_web/README.md
llama_index/readers/web/beautiful_soup_web/__init__.py
llama_index/readers/web/beautiful_soup_web/base.py
llama_index/readers/web/beautiful_soup_web/requirements.txt
llama_index/readers/web/browserbase_web/README.md
llama_index/readers/web/browserbase_web/__init__.py
llama_index/readers/web/browserbase_web/base.py
llama_index/readers/web/browserbase_web/requirements.txt
llama_index/readers/web/firecrawl_web/README.md
llama_index/readers/web/firecrawl_web/__init__.py
llama_index/readers/web/firecrawl_web/base.py
llama_index/readers/web/firecrawl_web/requirements.txt
llama_index/readers/web/hyperbrowser_web/README.md
llama_index/readers/web/hyperbrowser_web/__init__.py
llama_index/readers/web/hyperbrowser_web/base.py
llama_index/readers/web/hyperbrowser_web/requirements.txt
llama_index/readers/web/knowledge_base/README.md
llama_index/readers/web/knowledge_base/__init__.py
llama_index/readers/web/knowledge_base/base.py
llama_index/readers/web/knowledge_base/requirements.txt
llama_index/readers/web/main_content_extractor/README.md
llama_index/readers/web/main_content_extractor/__init__.py
llama_index/readers/web/main_content_extractor/base.py
llama_index/readers/web/main_content_extractor/requirements.txt
llama_index/readers/web/news/README.md
llama_index/readers/web/news/__init__.py
llama_index/readers/web/news/base.py
llama_index/readers/web/news/requirements.txt
llama_index/readers/web/olostep_web/README.md
llama_index/readers/web/olostep_web/base.py
llama_index/readers/web/olostep_web/requirements.txt
llama_index/readers/web/oxylabs_web/README.md
llama_index/readers/web/oxylabs_web/__init__.py
llama_index_readers_web-0.5.6.dist-info/METADATA
llama_index_readers_web-0.5.6.dist-info/WHEEL
llama_index_readers_web-0.5.6.dist-info/licenses/LICENSE
llama_index_readers_web-0.5.6.dist-info/RECORD
